sheet2graph/__init__.py
sheet2graph/__main__.py
sheet2graph/sheet2graph.py
sheet2graph/tests.py
sheet2graph-0.0.1.dist-info/LICENSE
sheet2graph-0.0.1.dist-info/METADATA
sheet2graph-0.0.1.dist-info/WHEEL
sheet2graph-0.0.1.dist-info/entry_points.txt
sheet2graph-0.0.1.dist-info/top_level.txt
sheet2graph-0.0.1.dist-info/RECORD
