Metadata-Version: 2.1
Name: sheet2graph
Version: 0.0.1
Summary: Generate graphs from spreadsheets
Home-page: https://github.com/fromzerotofullstack/sheet2graph
Author: Jesus Mejuto
Author-email: j@mejuto.co
License: UNKNOWN
Project-URL: Bug Tracker, https://github.com/fromzerotofullstack/sheet2graph/issues
Platform: UNKNOWN
Classifier: Programming Language :: Python :: 3
Classifier: License :: OSI Approved :: GNU Lesser General Public License v3 (LGPLv3)
Classifier: Operating System :: OS Independent
Requires-Python: >=3.6
Requires-Dist: kaleido
Requires-Dist: numpy
Requires-Dist: openpyxl
Requires-Dist: pandas
Requires-Dist: Pillow
Requires-Dist: plotly
Requires-Dist: requests
Requires-Dist: typeguard
